webnexa/__init__.py
webnexa/core.py
webnexa-0.1.0.dist-info/licenses/LICENSE
webnexa-0.1.0.dist-info/METADATA
webnexa-0.1.0.dist-info/WHEEL
webnexa-0.1.0.dist-info/top_level.txt
webnexa-0.1.0.dist-info/RECORD
