Metadata-Version: 2.4
Name: webnexa
Version: 0.1.0
Summary: A Python library for loading websites and asking questions using Hugging Face AI. Developed by Fardin Ibrahimi, Bachelor of Science in Computer Science and CEO of Humanoid Company. Humanoid Company specializes in developing AI applications and models that closely emulate human actions and decision-making approaches, with the mission statement 'Not Human, Beyond Human'. This library enables more accessible and innovative web interaction capabilities.
Home-page: https://github.com/yourusername/webnexa
Author: Fardin Ibrahimi
Author-email: Humanoid <farib5000@gmail.com>
License: MIT
Project-URL: Homepage, https://github.com/yourusername/webnexa
Project-URL: Documentation, https://github.com/yourusername/webnexa#readme
Project-URL: Repository, https://github.com/yourusername/webnexa
Project-URL: Issues, https://github.com/yourusername/webnexa/issues
Keywords: huggingface,ai,web-scraping,qa,llm,chatbot
Classifier: Development Status :: 4 - Beta
Classifier: Intended Audience :: Developers
Classifier: License :: OSI Approved :: MIT License
Classifier: Programming Language :: Python :: 3
Classifier: Programming Language :: Python :: 3.8
Classifier: Programming Language :: Python :: 3.9
Classifier: Programming Language :: Python :: 3.10
Classifier: Programming Language :: Python :: 3.11
Classifier: Programming Language :: Python :: 3.12
Classifier: Topic :: Software Development :: Libraries :: Python Modules
Classifier: Topic :: Scientific/Engineering :: Artificial Intelligence
Requires-Python: >=3.8
License-File: LICENSE
Requires-Dist: llama-index>=0.10.0
Requires-Dist: llama-index-readers-web>=0.1.0
Requires-Dist: requests>=2.31.0
Dynamic: author
Dynamic: home-page
Dynamic: license-file
Dynamic: requires-python
